setup.cfg
setup.py
sphere/__init__.py
sphere/sphere.py
vMF/__init__.py
vMF/vMF.py
vMF.egg-info/PKG-INFO
vMF.egg-info/SOURCES.txt
vMF.egg-info/dependency_links.txt
vMF.egg-info/top_level.txt