Metadata-Version: 2.1
Name: vMF
Version: 0.1.1
Summary: von Mises - Fisher distribution
Home-page: https://github.com/cescalara/vMF
Author: Francesca Capel
Author-email: capel.francesca@gmail.com
Keywords: statistics
